lazy_streams.py
lazy_streams-1.0.1.dist-info/LICENSE
lazy_streams-1.0.1.dist-info/METADATA
lazy_streams-1.0.1.dist-info/WHEEL
lazy_streams-1.0.1.dist-info/top_level.txt
lazy_streams-1.0.1.dist-info/RECORD
