Metadata-Version: 2.1
Name: lazy-streams
Version: 1.0.1
Summary: Java inspired streams in Python
Author-email: Steve Brettschneider <steve@bluehousefamily.com>, Rémi Desgrange <remi.desgrange@camptocamp.com>
License: GNU AFFERO GENERAL PUBLIC LICENSE
Project-URL: Homepage, https://github.com/brettschneider/python_lazy_streams
Project-URL: Bug Tracker, https://github.com/brettschneider/python_lazy_streams/issues
Classifier: Programming Language :: Python :: 3
Classifier: License :: OSI Approved :: GNU General Public License v3 or later (GPLv3+)
Classifier: Operating System :: OS Independent
Classifier: Development Status :: 5 - Production/Stable
Requires-Python: >=3.8
License-File: LICENSE
Requires-Dist: promise-keeper (~=1.0)
